cs/fileutils.py
cs_fileutils-20250528.dist-info/WHEEL
cs_fileutils-20250528.dist-info/METADATA
cs_fileutils-20250528.dist-info/RECORD
