Metadata-Version: 2.4
Name: cs-fileutils
Version: 20250528
Summary: My grab bag of convenience functions for files and filenames/pathnames.
Keywords: python2,python3
Author-email: Cameron Simpson <cs@cskk.id.au>
Classifier: Programming Language :: Python
Classifier: Programming Language :: Python :: 2
Classifier: Programming Language :: Python :: 3
Classifier: Development Status :: 4 - Beta
Classifier: Intended Audience :: Developers
Classifier: Operating System :: OS Independent
Classifier: Topic :: Software Development :: Libraries :: Python Modules
Classifier: License :: OSI Approved :: GNU General Public License v3 or later (GPLv3+)
Requires-Dist: cs.buffer>=20250428
Requires-Dist: cs.context>=20250528
Requires-Dist: cs.deco>=20250513
Requires-Dist: cs.filestate>=20181107
Requires-Dist: cs.fs>=20220429
Requires-Dist: cs.gimmicks>=20211208
Requires-Dist: cs.lex>=20200914
Requires-Dist: cs.logutils>=20250323
Requires-Dist: cs.pfx>=20210731
Requires-Dist: cs.progress>=20250528
Requires-Dist: cs.py3>=20220523
Requires-Dist: cs.range>=20230701
Requires-Dist: cs.resources>=20250325
Requires-Dist: cs.result>=20250306
Requires-Dist: cs.threads>=20250528
Requires-Dist: cs.units>=20250528
Project-URL: MonoRepo Commits, https://bitbucket.org/cameron_simpson/css/commits/branch/main
Project-URL: Monorepo Git Mirror, https://github.com/cameron-simpson/css
Project-URL: Monorepo Hg/Mercurial Mirror, https://hg.sr.ht/~cameron-simpson/css
Project-URL: Source, https://github.com/cameron-simpson/css/blob/main/lib/python/cs/fileutils.py
